ex4nicegui/__init__.py
ex4nicegui/version.py
ex4nicegui/bi/__init__.py
ex4nicegui/bi/dataSource.py
ex4nicegui/bi/dataSourceFacade.py
ex4nicegui/bi/index.py
ex4nicegui/bi/protocols.py
ex4nicegui/bi/types.py
ex4nicegui/bi/elements/__init__.py
ex4nicegui/bi/elements/containers.py
ex4nicegui/bi/elements/layouts.py
ex4nicegui/bi/elements/models.py
ex4nicegui/bi/elements/text.py
ex4nicegui/bi/elements/ui_aggrid.py
ex4nicegui/bi/elements/ui_date_picker.js
ex4nicegui/bi/elements/ui_date_picker.py
ex4nicegui/bi/elements/ui_echarts.py
ex4nicegui/bi/elements/ui_radio.py
ex4nicegui/bi/elements/ui_range.py
ex4nicegui/bi/elements/ui_select.py
ex4nicegui/bi/elements/ui_slider.py
ex4nicegui/bi/elements/ui_table.py
ex4nicegui/experimental_/__init__.py
ex4nicegui/experimental_/gridLayout/__init__.py
ex4nicegui/experimental_/gridLayout/index.py
ex4nicegui/helper/__init__.py
ex4nicegui/helper/client_instance_locker.py
ex4nicegui/layout/__init__.py
ex4nicegui/layout/gridFlex/GridFlex.js
ex4nicegui/layout/gridFlex/__init__.py
ex4nicegui/layout/gridFlex/gridFlex.py
ex4nicegui/layout/gridFlex/utils.py
ex4nicegui/layout/rxFlex/__init__.py
ex4nicegui/layout/rxFlex/index.py
ex4nicegui/layout/rxFlex/types.py
ex4nicegui/libs/__init__.py
ex4nicegui/libs/d3/__init__.py
ex4nicegui/libs/d3/d3-color.ems.js
ex4nicegui/libs/d3/d3-dispatch.ems.js
ex4nicegui/libs/d3/d3-drag.ems.js
ex4nicegui/libs/d3/d3-ease.ems.js
ex4nicegui/libs/d3/d3-interpolate.ems.js
ex4nicegui/libs/d3/d3-selection.ems.js
ex4nicegui/libs/d3/d3-timer.ems.js
ex4nicegui/libs/d3/d3-transition.ems.js
ex4nicegui/libs/d3/d3-zoom.ems.js
ex4nicegui/reactive/__init__.py
ex4nicegui/reactive/_vmodel.py
ex4nicegui/reactive/base.py
ex4nicegui/reactive/deferredTask.py
ex4nicegui/reactive/empty.js
ex4nicegui/reactive/empty.py
ex4nicegui/reactive/fileWatcher.py
ex4nicegui/reactive/q_pagination.py
ex4nicegui/reactive/rxui.py
ex4nicegui/reactive/scopedStyle.js
ex4nicegui/reactive/scopedStyle.py
ex4nicegui/reactive/transitionGroup.js
ex4nicegui-0.9.0.dist-info/METADATA
ex4nicegui-0.9.0.dist-info/WHEEL
ex4nicegui-0.9.0.dist-info/licenses/LICENSE
ex4nicegui-0.9.0.dist-info/RECORD
