Metadata-Version: 2.4
Name: ex4nicegui
Version: 0.9.0
Summary: Extension library based on nicegui, providing data responsive,BI functionality modules.
Author-email: CrystalWindSnake <568166495@qq.com>
License-Expression: MIT
License-File: LICENSE
Keywords: ex4nicegui,gui,nicegui,ui,web,webui
Requires-Python: >=3.9
Requires-Dist: executing~=2.0.1
Requires-Dist: nicegui~=3.0.0
Requires-Dist: signe~=0.4.22
